change_logs/__init__.py
change_logs/admin.py
change_logs/apps.py
change_logs/models.py
change_logs/urls.py
change_logs/views.py
change_logs/migrations/0001_initial.py
change_logs/migrations/__init__.py
change_logs/migrations/__pycache__/0001_initial.cpython-311.pyc
change_logs/migrations/__pycache__/0002_alter_changelog_date.cpython-311.pyc
change_logs/migrations/__pycache__/0002_alter_changelog_version.cpython-311.pyc
change_logs/migrations/__pycache__/0003_alter_changelog_version.cpython-311.pyc
change_logs/migrations/__pycache__/__init__.cpython-311.pyc
change_logs/templates/change_logs/detail.html
change_logs/templates/change_logs/list.html
change_logs_django-1.0.3.dist-info/LICENSE
change_logs_django-1.0.3.dist-info/METADATA
change_logs_django-1.0.3.dist-info/WHEEL
change_logs_django-1.0.3.dist-info/top_level.txt
change_logs_django-1.0.3.dist-info/RECORD
